yopmail/__init__.py
yopmail/yopmail.py
yopmail-1.9.dist-info/METADATA
yopmail-1.9.dist-info/WHEEL
yopmail-1.9.dist-info/top_level.txt
yopmail-1.9.dist-info/RECORD
