Metadata-Version: 2.1
Name: yopmail
Version: 1.9
Summary: A Python module to get mails from a Yopmail inbox, save them
Home-page: https://github.com/rklf/yopmail
Author: rklf
Author-email: 11515950+rklf@users.noreply.github.com
License: MIT
Keywords: yopmail get mails retrieve scrap emails
Platform: UNKNOWN
Requires-Python: >=3.10
Requires-Dist: beautifulsoup4
Requires-Dist: requests
